niceTouch/__init__.py
niceTouch/devices.py
niceTouch/niceTouch.py
niceTouch/screens.py
niceTouch/state.py
niceTouch/touchPanels.py
niceTouch-2019.2.10.1.data/scripts/nt
niceTouch-2019.2.10.1.dist-info/DESCRIPTION.rst
niceTouch-2019.2.10.1.dist-info/METADATA
niceTouch-2019.2.10.1.dist-info/RECORD
niceTouch-2019.2.10.1.dist-info/WHEEL
niceTouch-2019.2.10.1.dist-info/metadata.json
niceTouch-2019.2.10.1.dist-info/top_level.txt
