Metadata-Version: 2.0
Name: niceTouch
Version: 2019.2.10.1
Summary: UNKNOWN
Home-page: https://github.com/ksandom/niceTouch
Author: Kevin Sandom
Author-email: kjsandom@gmail.com
License: UNKNOWN
Platform: UNKNOWN
Requires-Dist: PyYAML
